mcpserver/__init__.py
mcpserver/app.py
mcpserver/defaults.py
mcpserver/logger.py
mcpserver/metrics.py
mcpserver/version.py
mcpserver/_logger/__init__.py
mcpserver/_logger/generate.py
mcpserver/_logger/logger.py
mcpserver/cli/__init__.py
mcpserver/cli/args.py
mcpserver/cli/logging.py
mcpserver/cli/manager.py
mcpserver/cli/start.py
mcpserver/core/__init__.py
mcpserver/core/config.py
mcpserver/core/execution.py
mcpserver/db/__init__.py
mcpserver/db/base.py
mcpserver/db/filesystem.py
mcpserver/db/sqlite.py
mcpserver/logger/__init__.py
mcpserver/logger/generate.py
mcpserver/logger/logger.py
mcpserver/middleware/__init__.py
mcpserver/middleware/requests.py
mcpserver/middleware/token_auth.py
mcpserver/routes/__init__.py
mcpserver/routes/views.py
mcpserver/tools/__init__.py
mcpserver/tools/base.py
mcpserver/tools/decorator.py
mcpserver/tools/manager.py
mcpserver/tools/prompts.py
mcpserver/tools/result.py
mcpserver/tools/simple/__init__.py
mcpserver/tools/simple/tool.py
mcpserver/tools/status/__init__.py
mcpserver/tools/status/prompts.py
mcpserver/tools/status/tool.py
mcpserver/ui/__init__.py
mcpserver/ui/base.py
mcpserver/ui/screens.py
mcpserver/ui/adapters/__init__.py
mcpserver/ui/adapters/cli.py
mcpserver/ui/adapters/tui.py
mcpserver/ui/adapters/web.py
mcpserver/utils/__init__.py
mcpserver/utils/fileio.py
mcpserver/utils/render.py
mcpserver/utils/text.py
mcpserver/utils/timer.py
mcp_serve-0.0.13.dist-info/LICENSE
mcp_serve-0.0.13.dist-info/METADATA
mcp_serve-0.0.13.dist-info/NOTICE
mcp_serve-0.0.13.dist-info/WHEEL
mcp_serve-0.0.13.dist-info/entry_points.txt
mcp_serve-0.0.13.dist-info/top_level.txt
mcp_serve-0.0.13.dist-info/RECORD
