Metadata-Version: 2.1
Name: mcp-serve
Version: 0.0.13
Summary: Agentic server to support MCP tools for science
Home-page: https://github.com/converged-computing/mcp-server
Author: Vanessa Sochat
Author-email: vsoch@users.noreply.github.com
Maintainer: Vanessa Sochat
License: LICENSE
Keywords: cluster,orchestration,mcp,server,agents
Classifier: Intended Audience :: Science/Research
Classifier: Intended Audience :: Developers
Classifier: License :: OSI Approved :: Mozilla Public License 2.0 (MPL 2.0)
Classifier: Programming Language :: C
Classifier: Programming Language :: Python
Classifier: Topic :: Software Development
Classifier: Topic :: Scientific/Engineering
Classifier: Operating System :: Unix
Classifier: Programming Language :: Python :: 3.11
License-File: LICENSE
License-File: NOTICE
Requires-Dist: jsonschema
Requires-Dist: Jinja2
Requires-Dist: uvicorn
Requires-Dist: mcp
Requires-Dist: fastmcp
Requires-Dist: requests
Requires-Dist: fastapi
Requires-Dist: rich
Requires-Dist: textual
Provides-Extra: all
Requires-Dist: jsonschema ; extra == 'all'
Requires-Dist: Jinja2 ; extra == 'all'
Requires-Dist: uvicorn ; extra == 'all'
Requires-Dist: mcp ; extra == 'all'
Requires-Dist: fastmcp ; extra == 'all'
Requires-Dist: requests ; extra == 'all'
Requires-Dist: fastapi ; extra == 'all'
Requires-Dist: rich ; extra == 'all'
Requires-Dist: textual ; extra == 'all'
Requires-Dist: pytest >=4.6.2 ; extra == 'all'
